charms/kubernetes_snaps.py
charms_kubernetes_snaps-0.0.1.dist-info/METADATA
charms_kubernetes_snaps-0.0.1.dist-info/WHEEL
charms_kubernetes_snaps-0.0.1.dist-info/licenses/LICENSE
charms_kubernetes_snaps-0.0.1.dist-info/RECORD
