Metadata-Version: 2.4
Name: charms.kubernetes-snaps
Version: 0.0.1
Summary: Charm library for installing and configuring Kubernetes snaps
Project-URL: Homepage, https://github.com/charmed-kubernetes/charm-lib-kubernetes-snaps
Project-URL: Bug Tracker, https://github.com/charmed-kubernetes/charm-lib-kubernetes-snaps/issues
Author-email: Adam Dyess <adam.dyess@canonical.com>, Mateo Florido <mateo.florido@canonical.com>
License-File: LICENSE
Classifier: License :: OSI Approved :: Apache Software License
Classifier: Programming Language :: Python :: 3
Requires-Python: >=3.8
Requires-Dist: charms-contextual-status
Requires-Dist: ops
Requires-Dist: packaging
Requires-Dist: pyyaml
